Metadata-Version: 1.0
Name: greg-scraper
Version: 1.0.1
Summary: Web Scraper
Home-page: https://github.com/GregoryPevnev/python-package
Author: Greg Pevnev
Author-email: UNKNOWN
License: UNKNOWN
Platform: UNKNOWN
